crypto_com_agent_plugin_telegram/__init__.py
crypto_com_agent_plugin_telegram/telegram.py
cryptocom_agent_plugin_telegram-1.1.6.dist-info/METADATA
cryptocom_agent_plugin_telegram-1.1.6.dist-info/WHEEL
cryptocom_agent_plugin_telegram-1.1.6.dist-info/entry_points.txt
cryptocom_agent_plugin_telegram-1.1.6.dist-info/RECORD
